{
    "FIBRAMQ12": {
        "LTV": null,
        "Ocupacion": null,
        "Metros_Cuadrados": null,
        "Propiedades": "9",
        "fuente": "2026-Reporte-T1-Fibra-Macquarie.pdf",
        "periodo": "1T2026"
    },
    "EDUCA": {
        "LTV": null,
        "Ocupacion": null,
        "Metros_Cuadrados": null,
        "Propiedades": "38",
        "fuente": "2026-Reporte-T1-Fibra-Educa.pdf",
        "periodo": "1T2026"
    },
    "PLUS": {
        "LTV": null,
        "Ocupacion": "95.5%",
        "Metros_Cuadrados": "85,654",
        "Propiedades": "22",
        "fuente": "2026-Reporte-T1-Fibra-Plus.pdf",
        "periodo": "1T2026"
    },
    "STORAGE": {
        "LTV": null,
        "Ocupacion": null,
        "Metros_Cuadrados": null,
        "Propiedades": "44",
        "fuente": "2026-Reporte-T1-Fibra-Storage.pdf",
        "periodo": "1T2026"
    },
    "NEXT": {
        "LTV": null,
        "Ocupacion": null,
        "Metros_Cuadrados": null,
        "Propiedades": "6",
        "fuente": "2026-Reporte-T1-Fibra-Next.pdf",
        "periodo": "1T2026"
    },
    "FUNO11": {
        "LTV": null,
        "Ocupacion": null,
        "Metros_Cuadrados": null,
        "Propiedades": "8",
        "fuente": "2026-Reporte-T1-FUNO.pdf",
        "periodo": "1T2026"
    },
    "ESP": {
        "LTV": null,
        "Ocupacion": null,
        "Metros_Cuadrados": null,
        "Propiedades": "199",
        "fuente": "Fibra-SOMA-1T26-ESP.pdf",
        "periodo": "1T2026"
    },
    "UPSITE": {
        "LTV": null,
        "Ocupacion": null,
        "Metros_Cuadrados": null,
        "Propiedades": "6",
        "fuente": "2026-Reporte-T1-Fibra-Upsite.pdf",
        "periodo": "1T2026"
    },
    "FIBRAPL14": {
        "LTV": null,
        "Ocupacion": "97.0%",
        "Metros_Cuadrados": null,
        "Propiedades": "516",
        "fuente": "2026-Reporte-T1-Fibra-Prologis.pdf",
        "periodo": "1T2026"
    },
    "FMTY14": {
        "LTV": null,
        "Ocupacion": null,
        "Metros_Cuadrados": null,
        "Propiedades": "120",
        "fuente": "2026-Reporte-T1-Fibra-Mty.pdf",
        "periodo": "1T2026"
    },
    "DANHOS13": {
        "LTV": null,
        "Ocupacion": "10.8%",
        "Metros_Cuadrados": null,
        "Propiedades": null,
        "fuente": "2026-Reporte-T1-Fibra-Danhos.pdf",
        "periodo": "1T2026"
    },
    "FNOVA17": {
        "LTV": null,
        "Ocupacion": "100%",
        "Metros_Cuadrados": null,
        "Propiedades": "12",
        "fuente": "2026-Reporte-T1-Fibra-Nova.pdf",
        "periodo": "1T2026"
    },
    "INN": {
        "LTV": "28.6%",
        "Ocupacion": "53.6%",
        "Metros_Cuadrados": null,
        "Propiedades": "32",
        "fuente": "2026-Reporte-T1-Fibra-Inn.pdf",
        "periodo": "1T2026"
    },
    "FIBRAHOTEL": {
        "LTV": null,
        "Ocupacion": null,
        "Metros_Cuadrados": null,
        "Propiedades": null,
        "fuente": "2026-Reporte-T1-FibraHotel.pdf",
        "periodo": "1T2026"
    },
    "FIBRASHOP": {
        "LTV": null,
        "Ocupacion": null,
        "Metros_Cuadrados": null,
        "Propiedades": null,
        "fuente": "2026-Reporte-T1-FibraShop.pdf",
        "periodo": "1T2026"
    }
}